shard/__init__.py
shard/main.py
shard/openai_api.py
shard/utils.py
shard/grpc/__init__.py
shard/grpc/mlx_tensor_pb2.py
shard/grpc/mlx_tensor_pb2_grpc.py
shard/protos/mlx_tensor.proto
shard/server/__init__.py
shard/server/server.py
shard/server/model/__init__.py
shard/server/model/base.py
shard/server/model/deepseek_v2.py
shard/server/model/gemma2.py
shard/server/model/llama.py
shard/static/app.js
shard/static/index.html
shard/static/styles.css
mlx_sharding-0.1.3.dist-info/METADATA
mlx_sharding-0.1.3.dist-info/WHEEL
mlx_sharding-0.1.3.dist-info/entry_points.txt
mlx_sharding-0.1.3.dist-info/top_level.txt
mlx_sharding-0.1.3.dist-info/RECORD
