Metadata-Version: 2.1
Name: mlx-sharding
Version: 0.1.3
Summary: A package for MLX model sharding and distributed inference
Home-page: https://github.com/mzbac/mlx_sharding
Author: Anchen
Author-email: li.anchen.au@gmail.com
Requires-Python: >=3.12.0
Requires-Dist: mlx
Requires-Dist: mlx-lm >=0.16.1
Requires-Dist: numpy
Requires-Dist: grpcio
Requires-Dist: grpcio-tools
Requires-Dist: transformers
Requires-Dist: protobuf
